Workbook

Sheet Raw_Sales_Data
A1: Order_ID | B1: Order_Date | C1: Customer | D1: City | E1: Category | F1: Product | G1: Quantity | H1: Unit_Price | I1: Salesperson | J1: Payment_Method
A2: 1001 | B2: 46025 | C2: Ali Khan | D2: Karachi | E2: Electronics | F2: Laptop | G2: 2 | H2: 85000 | I2: Ahmed | J2: Card
A3: 1002 | B3: 46027 | C3: Sara Ahmed | D3: Lahore | E3: Furniture | F3: Office Chair | G3: 5 | H3: 12000 | I3: Bilal | J3: Cash
A4: 1003 | B4: 46030 | C4: Hamza Ali | D4: Karachi | E4: Electronics | F4: Wireless Mouse | G4: 10 | H4: 2500 | I4: Ahmed | J4: Card
A5: 1004 | B5: 46034 | C5: Ayesha Malik | D5: Islamabad | E5: Clothing | F5: Jacket | G5: 3 | H5: 8500 | I5: Sana | J5: Bank Transfer
A6: 1005 | B6: 46040 | C6: Usman Raza | D6: Lahore | E6: Electronics | F6: Monitor | G6: 2 | H6: 32000 | I6: Bilal | J6: Card
A7: 1006 | B7: 46044 | C7: Hina Shah | D7: Karachi | E7: Furniture | F7: Desk | G7: 1 | H7: 45000 | I7: Ahmed | J7: Cash
A8: 1007 | B8: 46055 | C8: Omar Farooq | D8: Islamabad | E8: Clothing | F8: Shoes | G8: 4 | H8: 6500 | I8: Sana | J8: Card
A9: 1008 | B9: 46059 | C9: Zainab Noor | D9: Karachi | E9: Electronics | F9: Keyboard | G9: 6 | H9: 4500 | I9: Ahmed | J9: Bank Transfer
A10: 1009 | B10: 46063 | C10: Bilal Hussain | D10: Lahore | E10: Furniture | F10: Bookshelf | G10: 2 | H10: 28000 | I10: Bilal | J10: Cash
A11: 1010 | B11: 46067 | C11: Mariam Iqbal | D11: Karachi | E11: Clothing | F11: Jeans | G11: 5 | H11: 5500 | I11: Sana | J11: Card
A12: 1011 | B12: 46072 | C12: Danish Khan | D12: Islamabad | E12: Electronics | F12: Tablet | G12: 2 | H12: 48000 | I12: Hamza | J12: Card
A13: 1012 | B13: 46078 | C13: Fatima Zahid | D13: Lahore | E13: Furniture | F13: Dining Table | G13: 1 | H13: 95000 | I13: Bilal | J13: Bank Transfer
... A51: 1050 | B51: 46264 | C51: Imran Khan | D51: Karachi | E51: Furniture | F51: Sofa | G51: 2 | H51: 128000 | I51: Hamza | J51: Bank Transfer

Sheet Analysis
A1: Revenue | B1: Total_Sales
A2: =Raw_Sales_Data!H2*Raw_Sales_Data!G2 -> 170000 | B2: =SUM(Analysis!A2:A51) -> 5189800
A3: =Raw_Sales_Data!H3*Raw_Sales_Data!G3 -> 60000
A4: =Raw_Sales_Data!H4*Raw_Sales_Data!G4 -> 25000 | B4: Total_Quantity_Sold
A5: =Raw_Sales_Data!H5*Raw_Sales_Data!G5 -> 25500 | B5: =SUM(Raw_Sales_Data!G2:G51) -> 300
A6: =Raw_Sales_Data!H6*Raw_Sales_Data!G6 -> 64000
A7: =Raw_Sales_Data!H7*Raw_Sales_Data!G7 -> 45000 | B7: Average_Order_Revenue
A8: =Raw_Sales_Data!H8*Raw_Sales_Data!G8 -> 26000 | B8: =AVERAGE(Analysis!A:A) -> 103796
A9: =Raw_Sales_Data!H9*Raw_Sales_Data!G9 -> 27000
A10: =Raw_Sales_Data!H10*Raw_Sales_Data!G10 -> 56000 | B10: Highest_Order_Value
A11: =Raw_Sales_Data!H11*Raw_Sales_Data!G11 -> 27500 | B11: =MAX(Analysis!A:A) -> 324000
A12: =Raw_Sales_Data!H12*Raw_Sales_Data!G12 -> 96000
A13: =Raw_Sales_Data!H13*Raw_Sales_Data!G13 -> 95000
A14: =Raw_Sales_Data!H14*Raw_Sales_Data!G14 -> 92000
A15: =Raw_Sales_Data!H15*Raw_Sales_Data!G15 -> 33600
A16: =Raw_Sales_Data!H16*Raw_Sales_Data!G16 -> 165000
A17: =Raw_Sales_Data!H17*Raw_Sales_Data!G17 -> 125000
A18: =Raw_Sales_Data!H18*Raw_Sales_Data!G18 -> 38400
A19: =Raw_Sales_Data!H19*Raw_Sales_Data!G19 -> 52500
A20: =Raw_Sales_Data!H20*Raw_Sales_Data!G20 -> 54000
A21: =Raw_Sales_Data!H21*Raw_Sales_Data!G21 -> 36000
A22: =Raw_Sales_Data!H22*Raw_Sales_Data!G22 -> 90000
A23: =Raw_Sales_Data!H23*Raw_Sales_Data!G23 -> 115000
... A51: =Raw_Sales_Data!H51*Raw_Sales_Data!G51 -> 256000
